torch_staintools/__init__.py
torch_staintools/loggers.py
torch_staintools/version.py
torch_staintools/augmentor/__init__.py
torch_staintools/augmentor/base.py
torch_staintools/augmentor/factory.py
torch_staintools/base_module/__init__.py
torch_staintools/base_module/base.py
torch_staintools/cache/__init__.py
torch_staintools/cache/base.py
torch_staintools/cache/tensor_cache.py
torch_staintools/functional/__init__.py
torch_staintools/functional/eps.py
torch_staintools/functional/conversion/__init__.py
torch_staintools/functional/conversion/lab.py
torch_staintools/functional/conversion/od.py
torch_staintools/functional/optimization/__init__.py
torch_staintools/functional/optimization/dict_learning.py
torch_staintools/functional/optimization/solver.py
torch_staintools/functional/optimization/sparse_util.py
torch_staintools/functional/stain_extraction/__init__.py
torch_staintools/functional/stain_extraction/extractor.py
torch_staintools/functional/stain_extraction/factory.py
torch_staintools/functional/stain_extraction/macenko.py
torch_staintools/functional/stain_extraction/utils.py
torch_staintools/functional/stain_extraction/vahadane.py
torch_staintools/functional/tissue_mask/__init__.py
torch_staintools/functional/utility/__init__.py
torch_staintools/functional/utility/implementation.py
torch_staintools/normalizer/__init__.py
torch_staintools/normalizer/base.py
torch_staintools/normalizer/factory.py
torch_staintools/normalizer/reinhard.py
torch_staintools/normalizer/separation.py
torch_staintools-1.0.4.dist-info/LICENSE
torch_staintools-1.0.4.dist-info/METADATA
torch_staintools-1.0.4.dist-info/WHEEL
torch_staintools-1.0.4.dist-info/top_level.txt
torch_staintools-1.0.4.dist-info/RECORD
