Metadata-Version: 2.1
Name: torch-staintools
Version: 1.0.4
Summary: GPU-accelerated stain normalization and augmentation
Home-page: https://github.com/CielAl/torch-staintools
Author: Y Z
Author-email: cielmercy@gmail.com
License: MIT
Requires-Python: >=3.10
License-File: LICENSE
Requires-Dist: opencv-python
Requires-Dist: numpy ~=1.23.5
Requires-Dist: tqdm ~=4.65.0
Requires-Dist: kornia ~=0.7.0
Requires-Dist: scipy ~=1.10.0
Requires-Dist: pillow ~=9.4.0
Requires-Dist: setuptools ~=65.6.3
Requires-Dist: scikit-image ~=0.19.3
Requires-Dist: torchvision
Requires-Dist: torch
